pythink/__init__.py
pythink/exceptions.py
pythink/logger.py
pythink/records.py
pythink/think_database.py
pythink/think_model.py
pythink/think_table.py
pythink/util.py
pythink-0.0.9.dist-info/METADATA
pythink-0.0.9.dist-info/WHEEL
pythink-0.0.9.dist-info/top_level.txt
pythink-0.0.9.dist-info/RECORD
