Metadata-Version: 2.1
Name: pythink
Version: 0.0.9
Summary: simple CURD of mysql for python
Home-page: https://github.com/mouday/PyThink
Author: Peng Shiyu
Author-email: pengshiyuyx@gmail.com
License: UNKNOWN
Platform: UNKNOWN
Classifier: Programming Language :: Python :: 2.7
Classifier: Programming Language :: Python :: 3.6
Classifier: License :: OSI Approved :: MIT License
Classifier: Operating System :: OS Independent
Requires-Dist: SQLAlchemy (>=1.2.8)
Requires-Dist: PyMySQL (>=0.9.3)
